orb/__init__.py
orb/py.typed
orb/api/__init__.py
orb/api/tk.py
orb/cli/__init__.py
orb/cli/virtual.py
orb/examples/__init__.py
orb/examples/async_openai.py
orb/examples/elevenlabs.py
orb/examples/openai.py
orb/impl/__init__.py
orb/impl/base.py
orb/impl/openai_elevenlabs.py
orb/utils/__init__.py
orb/utils/ai/__init__.py
openorb-0.0.2.dist-info/LICENSE
openorb-0.0.2.dist-info/METADATA
openorb-0.0.2.dist-info/WHEEL
openorb-0.0.2.dist-info/entry_points.txt
openorb-0.0.2.dist-info/top_level.txt
openorb-0.0.2.dist-info/RECORD
